puncover/__init__.py
puncover/backtrace_helper.py
puncover/builders.py
puncover/collector.py
puncover/gcc_tools.py
puncover/middleware.py
puncover/puncover.py
puncover/renderers.py
puncover/static/css/bootstrap.min.css
puncover/static/css/style.css
puncover/static/fonts/glyphicons-halflings-regular.eot
puncover/static/fonts/glyphicons-halflings-regular.svg
puncover/static/fonts/glyphicons-halflings-regular.ttf
puncover/static/fonts/glyphicons-halflings-regular.woff
puncover/static/fonts/glyphicons-halflings-regular.woff2
puncover/static/icons/Document_16x.svg
puncover/static/icons/Field_16x.svg
puncover/static/icons/FolderOpen_16x.svg
puncover/static/icons/Folder_16x.svg
puncover/static/icons/Method_16x.svg
puncover/static/icons/readme.md
puncover/static/js/bootstrap.min.js
puncover/templates/all_symbols.html.jinja
puncover/templates/base.html.jinja
puncover/templates/file.html.jinja
puncover/templates/folder.html.jinja
puncover/templates/lists.html.jinja
puncover/templates/overview.html.jinja
puncover/templates/rack.html.jinja
puncover/templates/symbol.html.jinja
puncover-0.7.0.dist-info/METADATA
puncover-0.7.0.dist-info/WHEEL
puncover-0.7.0.dist-info/entry_points.txt
puncover-0.7.0.dist-info/licenses/LICENSE.txt
puncover-0.7.0.dist-info/RECORD
