Metadata-Version: 2.4
Name: puncover
Version: 0.7.0
Summary: Analyses C/C++ build output for code size, static variables, and stack usage.
License-File: LICENSE.txt
Author: Hendrik Behrens
Author-email: hendrik.behrens@gmail.com
Requires-Python: >=3.9
Classifier: Development Status :: 5 - Production/Stable
Classifier: Intended Audience :: Developers
Classifier: Natural Language :: English
Classifier: Programming Language :: Python :: 3
Classifier: Programming Language :: Python :: 3.9
Classifier: Programming Language :: Python :: 3.10
Classifier: Programming Language :: Python :: 3.11
Classifier: Programming Language :: Python :: 3.12
Classifier: Programming Language :: Python :: 3.13
Classifier: Programming Language :: Python :: 3.14
Requires-Dist: Flask (==2.2.5)
Requires-Dist: jinja2 (==3.1.6)
Requires-Dist: werkzeug (==3.0.6)
Project-URL: Homepage, https://github.com/HBehrens/puncover
Project-URL: Repository, https://github.com/HBehrens/puncover
